yt_dlp_plugins/extractor/servustv.py
ytdlp_servustv-2025.10.11.dist-info/METADATA
ytdlp_servustv-2025.10.11.dist-info/WHEEL
ytdlp_servustv-2025.10.11.dist-info/licenses/LICENSE
ytdlp_servustv-2025.10.11.dist-info/RECORD
