Metadata-Version: 2.4
Name: ytdlp-servustv
Version: 2025.10.11
Summary: yt-dlp extractor for servustv.com
License-Expression: Unlicense
License-File: LICENSE
Keywords: yt-dlp,youtube-dl,servustv,extractors,plugins
Author: flashdagger
Author-email: flashdagger@googlemail.com
Requires-Python: >= 3.9
Classifier: Development Status :: 4 - Beta
Classifier: Programming Language :: Python :: 3
Classifier: Programming Language :: Python :: 3.7
Classifier: Programming Language :: Python :: 3.8
Classifier: Programming Language :: Python :: 3.9
Classifier: Programming Language :: Python :: 3.10
Classifier: Programming Language :: Python :: 3.11
Classifier: Programming Language :: Python :: Implementation
Classifier: Programming Language :: Python :: Implementation :: CPython
Classifier: Programming Language :: Python :: Implementation :: PyPy
Classifier: Operating System :: OS Independent
Classifier: Environment :: Console
Classifier: Environment :: Plugins
Classifier: Topic :: Multimedia :: Video
Requires-Dist: yt-dlp (>=2023.01.06)
